telegram_words_back_taker/telegram_words_back_taker.py
telegram_words_back_taker-1.dist-info/METADATA
telegram_words_back_taker-1.dist-info/WHEEL
telegram_words_back_taker-1.dist-info/top_level.txt
telegram_words_back_taker-1.dist-info/RECORD
